llama_index/readers/quip/__init__.py
llama_index/readers/quip/base.py
llama_index_readers_quip-0.3.1.dist-info/METADATA
llama_index_readers_quip-0.3.1.dist-info/WHEEL
llama_index_readers_quip-0.3.1.dist-info/licenses/LICENSE
llama_index_readers_quip-0.3.1.dist-info/RECORD
